[
  {
    "id": "AD256/0",
    "carbonIntensity": 0.5,
    "production": 1.2,
    "compressionAndStorage": 0.8,
    "transport": 0.3,
    "endUse": 0.4,
    "renewableEnergySource": "Wind",
    "geographicalCorrelation": true,
    "renewablesAdditionality": true,
    "temporalCorrelation": true,
    "productionGHGEmissionsClass": "Class A",
    "renewableOrigin": true,
    "wasteManagement": "Efficient",
    "waterConsumption": "Low",
    "mineralInput": "High",
    "socioEconomicImpact": "Positive",
    "landUse": "Minimal"
  },
  {
    "id": "AD257/0",
    "carbonIntensity": 2.0,
    "production": 3.5,
    "compressionAndStorage": 1.0,
    "transport": 1.5,
    "endUse": 2.0,
    "renewableEnergySource": "Solar",
    "geographicalCorrelation": false,
    "renewablesAdditionality": false,
    "temporalCorrelation": false,
    "productionGHGEmissionsClass": "Class B",
    "renewableOrigin": false,
    "wasteManagement": "Moderate",
    "waterConsumption": "High",
    "mineralInput": "Low",
    "socioEconomicImpact": "Neutral",
    "landUse": "Moderate"
  },
  {
    "id": "AD258/0",
    "carbonIntensity": 1.5,
    "production": 2.2,
    "compressionAndStorage": 2.5,
    "transport": 1.2,
    "endUse": 1.0,
    "renewableEnergySource": "Hydro",
    "geographicalCorrelation": true,
    "renewablesAdditionality": true,
    "temporalCorrelation": false,
    "productionGHGEmissionsClass": "Class A",
    "renewableOrigin": true,
    "wasteManagement": "Good",
    "waterConsumption": "Moderate",
    "mineralInput": "Medium",
    "socioEconomicImpact": "Positive",
    "landUse": "High"
  },
  {
    "id": "AD259/0",
    "carbonIntensity": 0.3,
    "production": 0.7,
    "compressionAndStorage": 0.5,
    "transport": 0.2,
    "endUse": 0.3,
    "renewableEnergySource": "Geothermal",
    "geographicalCorrelation": true,
    "renewablesAdditionality": false,
    "temporalCorrelation": true,
    "productionGHGEmissionsClass": "Class A",
    "renewableOrigin": true,
    "wasteManagement": "Excellent",
    "waterConsumption": "Very Low",
    "mineralInput": "Low",
    "socioEconomicImpact": "Very Positive",
    "landUse": "Minimal"
  },
  {
    "id": "AD260/0",
    "carbonIntensity": 1.8,
    "production": 2.0,
    "compressionAndStorage": 1.5,
    "transport": 1.0,
    "endUse": 1.2,
    "renewableEnergySource": "Biomass",
    "geographicalCorrelation": false,
    "renewablesAdditionality": true,
    "temporalCorrelation": false,
    "productionGHGEmissionsClass": "Class B",
    "renewableOrigin": true,
    "wasteManagement": "Moderate",
    "waterConsumption": "High",
    "mineralInput": "Medium",
    "socioEconomicImpact": "Neutral",
    "landUse": "Moderate"
  },
  {
    "id": "AD261/0",
    "carbonIntensity": 2.5,
    "production": 3.0,
    "compressionAndStorage": 2.0,
    "transport": 1.8,
    "endUse": 2.5,
    "renewableEnergySource": "Nuclear",
    "geographicalCorrelation": false,
    "renewablesAdditionality": false,
    "temporalCorrelation": false,
    "productionGHGEmissionsClass": "Class C",
    "renewableOrigin": false,
    "wasteManagement": "Poor",
    "waterConsumption": "Very High",
    "mineralInput": "High",
    "socioEconomicImpact": "Negative",
    "landUse": "High"
  },
  {
    "id": "AD262/0",
    "carbonIntensity": 1.0,
    "production": 1.5,
    "compressionAndStorage": 1.2,
    "transport": 0.9,
    "endUse": 1.1,
    "renewableEnergySource": "Tidal",
    "geographicalCorrelation": true,
    "renewablesAdditionality": true,
    "temporalCorrelation": true,
    "productionGHGEmissionsClass": "Class A",
    "renewableOrigin": true,
    "wasteManagement": "Good",
    "waterConsumption": "Low",
    "mineralInput": "Medium",
    "socioEconomicImpact": "Positive",
    "landUse": "Minimal"
  },
  {
    "id": "AD263/0",
    "carbonIntensity": 0.6,
    "production": 1.1,
    "compressionAndStorage": 0.7,
    "transport": 0.4,
    "endUse": 0.5,
    "renewableEnergySource": "Solar",
    "geographicalCorrelation": true,
    "renewablesAdditionality": true,
    "temporalCorrelation": true,
    "productionGHGEmissionsClass": "Class A",
    "renewableOrigin": true,
    "wasteManagement": "Very Good",
    "waterConsumption": "Low",
    "mineralInput": "High",
    "socioEconomicImpact": "Very Positive",
    "landUse": "Low"
  },
  {
    "id": "AD264/0",
    "carbonIntensity": 0.9,
    "production": 1.4,
    "compressionAndStorage": 1.0,
    "transport": 0.6,
    "endUse": 0.8,
    "renewableEnergySource": "Wind",
    "geographicalCorrelation": true,
    "renewablesAdditionality": false,
    "temporalCorrelation": false,
    "productionGHGEmissionsClass": "Class B",
    "renewableOrigin": false,
    "wasteManagement": "Good",
    "waterConsumption": "Moderate",
    "mineralInput": "Medium",
    "socioEconomicImpact": "Positive",
    "landUse": "Moderate"
  },
  {
    "id": "AD265/0",
    "carbonIntensity": 0.4,
    "production": 0.9,
    "compressionAndStorage": 0.6,
    "transport": 0.3,
    "endUse": 0.4,
    "renewableEnergySource": "Hydro",
    "geographicalCorrelation": true,
    "renewablesAdditionality": true,
    "temporalCorrelation": true,
    "productionGHGEmissionsClass": "Class A",
    "renewableOrigin": true,
    "wasteManagement": "Excellent",
    "waterConsumption": "Very Low",
    "mineralInput": "Low",
    "socioEconomicImpact": "Positive",
    "landUse": "Minimal"
  }
]
